LICENSE
README.md
setup.cfg
setup.py
elasticsearch_tools/__init__.py
elasticsearch_tools.egg-info/PKG-INFO
elasticsearch_tools.egg-info/SOURCES.txt
elasticsearch_tools.egg-info/dependency_links.txt
elasticsearch_tools.egg-info/requires.txt
elasticsearch_tools.egg-info/top_level.txt
elasticsearch_tools/connection/__init__.py
elasticsearch_tools/connection/connection.py
elasticsearch_tools/connection/sync_session_manager.py
elasticsearch_tools/connection/async_client/__init__.py
elasticsearch_tools/connection/async_client/async_session_manager.py
elasticsearch_tools/connection/async_client/connection.py
elasticsearch_tools/connection/base/__init__.py
elasticsearch_tools/connection/base/abc_session_manager.py
elasticsearch_tools/query/__init__.py
elasticsearch_tools/query/base.py
elasticsearch_tools/query/bool.py
elasticsearch_tools/query/search.py
examples/__init__.py
examples/example_bool_operations.py
examples/example_query_generate.py
examples/examples_queries.py
tests/__init__.py
tests/test_bool_query.py
tests/test_generate_query.py
tests/test_search_query.py