Metadata-Version: 2.1
Name: elasticsearch_tools
Version: 1.0.8
Summary: Python module for working with elasticsearch, create queries and connections 
Home-page: https://github.com/Karim90403/elasticsearch-tools/
Download-URL: https://github.com/Karim90403/elasticsearch-tools/archive/refs/heads/main.zip
Author: Karim90403
Author-email: karim90403@gmail.ru
License: Apache License, Version 2.0, see LICENSE file
Classifier: License :: OSI Approved :: Apache Software License
Classifier: Operating System :: OS Independent
Classifier: Intended Audience :: End Users/Desktop
Classifier: Intended Audience :: Developers
Classifier: Programming Language :: Python
Classifier: Programming Language :: Python :: 3
Classifier: Programming Language :: Python :: 3.6
Classifier: Programming Language :: Python :: 3.7
Classifier: Programming Language :: Python :: 3.8
Classifier: Programming Language :: Python :: 3.9
Classifier: Programming Language :: Python :: Implementation :: PyPy
Classifier: Programming Language :: Python :: Implementation :: CPython
License-File: LICENSE
Requires-Dist: elasticsearch
